{
  "dataBrands": ["Hồng Hà", "Thiên Long", "Bến Nghé"],
  "dataSlides": [
    {
      "id": "pr1",
      "classify": "butbi",
      "img": "Hinhanh/butbi/TL1.webp",
      "title": "Thiên Long",
      "more": ["Bút bi - Eco Style Thiên Long"],
      "color": ["Màu mực : xanh dương, đen"]
    },
    {
      "id": "pr10",
      "classify": "butbi",
      "img": "Hinhanh/butbi/HH2.webp",
      "title": "Hồng Hà",
      "more": ["Bút bi - Quốc dân Hồng Hà"],
      "color": ["Màu mực : xanh dương, đỏ & đen"]
    },
    {
      "id": "pr20",
      "classify": "butchi",
      "img": "Hinhanh/butchi/TL3.webp",
      "title": "Thiên Long",
      "more": ["Bút chì mỹ thuật Thiên Long 5B"],
      "color": [""]
    }
  ],
  "dataProducts": [
    {
      "id": "pr1",
      "classify": "butbi",
      "img": "Hinhanh/butbi/TL1.webp",
      "title": "Thiên Long",
      "color": ["xanh", "tím", "đỏ", "đen"],
      "price": [15000]
    },
    {
      "id": "pr2",
      "classify": "butbi",
      "img": "Hinhanh/butbi/TL2.webp",
      "title": "Thiên Long",
      "color": ["xanh", "tím", "đỏ", "đen"],
      "price": [15011]
    },
    {
      "id": "pr3",
      "classify": "butbi",
      "img": "Hinhanh/butbi/TL3.webp",
      "title": "Thiên Long",
      "color": ["xanh", "tím", "đỏ", "đen"],
      "price": [28734]
    },
    {
      "id": "pr4",
      "classify": "butbi",
      "img": "Hinhanh/butbi/TL4.webp",
      "title": "Thiên Long",
      "color": ["xanh", "tím", "đỏ", "đen"],
      "price": [39093]
    },
    {
      "id": "pr5",
      "classify": "butbi",
      "img": "Hinhanh/butbi/TL5.webp",
      "title": "Thiên Long",
      "color": ["xanh", "tím", "đỏ", "đen"],
      "price": [8650]
    },
    {
      "id": "pr6",
      "classify": "butbi",
      "img": "Hinhanh/butbi/TL6.webp",
      "title": "Thiên Long",
      "color": ["xanh", "tím", "đỏ", "đen"],
      "price": [33602]
    },
    {
      "id": "pr7",
      "classify": "butbi",
      "img": "Hinhanh/butbi/TL7.webp",
      "title": "Thiên Long",
      "color": ["xanh", "tím", "đỏ", "đen"],
      "price": [25082]
    },
    {
      "id": "pr8",
      "classify": "butbi",
      "img": "Hinhanh/butbi/TL8.webp",
      "title": "Thiên Long",
      "color": ["xanh", "tím", "đỏ", "đen"],
      "price": [42324]
    },
    {
      "id": "pr9",
      "classify": "butbi",
      "img": "Hinhanh/butbi/HH1.webp",
      "title": "Hồng Hà",
      "color": ["xanh", "tím", "đỏ", "đen"],
      "price": [31835]
    },
    {
      "id": "pr10",
      "classify": "butbi",
      "img": "Hinhanh/butbi/HH2.webp",
      "title": "Hồng Hà",
      "color": ["xanh", "tím", "đỏ", "đen"],
      "price": [26569]
    },
    {
      "id": "pr11",
      "classify": "butbi",
      "img": "Hinhanh/butbi/HH3.webp",
      "title": "Hồng Hà",
      "color": ["xanh", "tím", "đỏ", "đen"],
      "price": [13693]
    },
    {
      "id": "pr12",
      "classify": "butbi",
      "img": "Hinhanh/butbi/HH4.webp",
      "title": "Hồng Hà",
      "color": ["xanh", "tím", "đỏ", "đen"],
      "price": [27802]
    },
    {
      "id": "pr13",
      "classify": "butbi",
      "img": "Hinhanh/butbi/HH5.webp",
      "title": "Hồng Hà",
      "color": ["xanh", "tím", "đỏ", "đen"],
      "price": [41110]
    },
    {
      "id": "pr14",
      "classify": "butbi",
      "img": "Hinhanh/butbi/BN1.webp",
      "title": "Bến Nghé",
      "color": ["xanh", "tím", "đỏ", "đen"],
      "price": [17984]
    },
    {
      "id": "pr15",
      "classify": "butbi",
      "img": "Hinhanh/butbi/BN2.webp",
      "title": "Bến Nghé",
      "color": ["xanh", "tím", "đỏ", "đen"],
      "price": [18237]
    },
    {
      "id": "pr16",
      "classify": "butbi",
      "img": "Hinhanh/butbi/BN3.webp",
      "title": "Bến Nghé",
      "color": ["xanh", "tím", "đỏ", "đen"],
      "price": [36485]
    },
    {
      "id": "pr17",
      "classify": "butbi",
      "img": "Hinhanh/butbi/BN4.webp",
      "title": "Bến Nghé",
      "color": ["xanh", "tím", "đỏ", "đen"],
      "price": [26686]
    },

    {
      "id": "pr18",
      "classify": "butchi",
      "img": "Hinhanh/butchi/TL1.webp",
      "title": "Thiên Long",
      "color": ["xanh", "tím", "đỏ", "đen"],
      "price": [12000]
    },
    {
      "id": "pr19",
      "classify": "butchi",
      "img": "Hinhanh/butchi/TL2.webp",
      "title": "Thiên Long",
      "color": ["xanh", "tím", "đỏ", "đen"],
      "price": [15000]
    },
    {
      "id": "pr20",
      "classify": "butchi",
      "img": "Hinhanh/butchi/TL3.webp",
      "title": "Thiên Long",
      "color": ["xanh", "tím", "đỏ", "đen"],
      "price": [7000]
    },
    {
      "id": "pr21",
      "classify": "butchi",
      "img": "Hinhanh/butchi/TL4.webp",
      "title": "Thiên Long",
      "color": ["xanh", "tím", "đỏ", "đen"],
      "price": [10000]
    },
    {
      "id": "pr22",
      "classify": "butchi",
      "img": "Hinhanh/butchi/TL5.webp",
      "title": "Thiên Long",
      "color": ["xanh", "tím", "đỏ", "đen"],
      "price": [17000]
    },
    {
      "id": "pr23",
      "classify": "butchi",
      "img": "Hinhanh/butchi/TL6.webp",
      "title": "Thiên Long",
      "color": ["xanh", "tím", "đỏ", "đen"],
      "price": [6000]
    },
    {
      "id": "pr24",
      "classify": "butchi",
      "img": "Hinhanh/butchi/HH1.webp",
      "title": "Hồng Hà",
      "color": ["xanh", "tím", "đỏ", "đen"],
      "price": [13000]
    },
    {
      "id": "pr25",
      "classify": "butchi",
      "img": "Hinhanh/butchi/HH2.webp",
      "title": "Hồng Hà",
      "color": ["xanh", "tím", "đỏ", "đen"],
      "price": [11000]
    },
    {
      "id": "pr26",
      "classify": "butchi",
      "img": "Hinhanh/butchi/HH3.webp",
      "title": "Hồng Hà",
      "color": ["xanh", "tím", "đỏ", "đen"],
      "price": [9000]
    },
    {
      "id": "pr27",
      "classify": "butchi",
      "img": "Hinhanh/butchi/HH4.webp",
      "title": "Hồng Hà",
      "color": ["xanh", "tím", "đỏ", "đen"],
      "price": [5000]
    },
    {
      "id": "pr28",
      "classify": "butchi",
      "img": "Hinhanh/butchi/HH5.webp",
      "title": "Hồng Hà",
      "color": ["xanh", "tím", "đỏ", "đen"],
      "price": [14000]
    },
    {
      "id": "pr29",
      "classify": "butchi",
      "img": "Hinhanh/butchi/HH6.webp",
      "title": "Hồng Hà",
      "color": ["xanh", "tím", "đỏ", "đen"],
      "price": [20000]
    },

    {
      "id": "pr30",
      "classify": "butlong",
      "img": "Hinhanh/butlong/TL1.webp",
      "title": "Thiên Long",
      "color": ["xanh", "tím", "đỏ", "đen"],
      "price": [25000]
    },
    {
      "id": "pr31",
      "classify": "butlong",
      "img": "Hinhanh/butlong/TL2.webp",
      "title": "Thiên Long",
      "color": ["xanh", "tím", "đỏ", "đen"],
      "price": [25000]
    },
    {
      "id": "pr32",
      "classify": "butlong",
      "img": "Hinhanh/butlong/TL3.webp",
      "title": "Thiên Long",
      "color": ["xanh", "tím", "đỏ", "đen"],
      "price": [25000]
    },
    {
      "id": "pr33",
      "classify": "butlong",
      "img": "Hinhanh/butlong/TL4.webp",
      "title": "Thiên Long",
      "color": ["xanh", "tím", "đỏ", "đen"],
      "price": [25000]
    },
    {
      "id": "pr34",
      "classify": "butlong",
      "img": "Hinhanh/butlong/HH1.webp",
      "title": "Hồng Hà",
      "color": ["xanh", "tím", "đỏ", "đen"],
      "price": [27000]
    },
    {
      "id": "pr35",
      "classify": "butlong",
      "img": "Hinhanh/butlong/HH2.webp",
      "title": "Hồng Hà",
      "color": ["xanh", "tím", "đỏ", "đen"],
      "price": [27000]
    },
    {
      "id": "pr36",
      "classify": "butlong",
      "img": "Hinhanh/butlong/HH3.webp",
      "title": "Hồng Hà",
      "color": ["xanh", "tím", "đỏ", "đen"],
      "price": [27000]
    },
    {
      "id": "pr37",
      "classify": "butlong",
      "img": "Hinhanh/butlong/BN1.webp",
      "title": "Bến Nghé",
      "color": ["xanh", "tím", "đỏ", "đen"],
      "price": [26500]
    },
    {
      "id": "pr38",
      "classify": "butlong",
      "img": "Hinhanh/butlong/BN2.webp",
      "title": "Bến Nghé",
      "color": ["xanh", "tím", "đỏ", "đen"],
      "price": [26500]
    },
    {
      "id": "pr39",
      "classify": "butlong",
      "img": "Hinhanh/butlong/BN3.webp",
      "title": "Bến Nghé",
      "color": ["xanh", "tím", "đỏ", "đen"],
      "price": [26500]
    },
    {
      "id": "pr40",
      "classify": "butlong",
      "img": "Hinhanh/butlong/BN4.webp",
      "title": "Bến Nghé",
      "color": ["xanh", "tím", "đỏ", "đen"],
      "price": [26500]
    }
  ]
}
